simple_lan_scanner-1.0.1.dist-info/licenses/LICENSE
simple_scanner/__init__.py
simple_scanner/__main__.py
simple_scanner/cli.py
simple_scanner/gui.py
simple_scanner/models.py
simple_scanner/scanner.py
simple_lan_scanner-1.0.1.dist-info/METADATA
simple_lan_scanner-1.0.1.dist-info/WHEEL
simple_lan_scanner-1.0.1.dist-info/entry_points.txt
simple_lan_scanner-1.0.1.dist-info/top_level.txt
simple_lan_scanner-1.0.1.dist-info/RECORD
