Metadata-Version: 2.4
Name: simple_lan_scanner
Version: 1.0.1
Summary: A Python LAN scanning tool that uses nmap to discover devices on the local network
Author-email: Adam Zalewski <me@yamero.online>
License: MIT
Keywords: network,scanner,nmap,lan,monitoring
Classifier: Development Status :: 5 - Production/Stable
Classifier: Intended Audience :: System Administrators
Classifier: License :: OSI Approved :: MIT License
Classifier: Programming Language :: Python :: 3
Classifier: Programming Language :: Python :: 3.10
Classifier: Programming Language :: Python :: 3.11
Classifier: Programming Language :: Python :: 3.12
Classifier: Programming Language :: Python :: 3.13
Classifier: Topic :: System :: Networking :: Monitoring
Requires-Python: >=3.10
License-File: LICENSE
Provides-Extra: cli
Requires-Dist: click>=8.1; extra == "cli"
Provides-Extra: test
Requires-Dist: pytest>=7.0; extra == "test"
Requires-Dist: pytest-mock>=3.10; extra == "test"
Requires-Dist: pytest-cov>=4.0; extra == "test"
Dynamic: license-file
